odoo/addons/sale_line_returned_qty_mrp/README.rst
odoo/addons/sale_line_returned_qty_mrp/__init__.py
odoo/addons/sale_line_returned_qty_mrp/__manifest__.py
odoo/addons/sale_line_returned_qty_mrp/i18n/it.po
odoo/addons/sale_line_returned_qty_mrp/i18n/sale_line_returned_qty_mrp.pot
odoo/addons/sale_line_returned_qty_mrp/models/__init__.py
odoo/addons/sale_line_returned_qty_mrp/models/sale_order_line.py
odoo/addons/sale_line_returned_qty_mrp/readme/CONTRIBUTORS.md
odoo/addons/sale_line_returned_qty_mrp/readme/DESCRIPTION.md
odoo/addons/sale_line_returned_qty_mrp/static/description/icon.png
odoo/addons/sale_line_returned_qty_mrp/static/description/index.html
odoo/addons/sale_line_returned_qty_mrp/tests/__init__.py
odoo/addons/sale_line_returned_qty_mrp/tests/test_sale_line_returned_qty_mrp.py
odoo_addon_sale_line_returned_qty_mrp-18.0.1.0.0.2.dist-info/METADATA
odoo_addon_sale_line_returned_qty_mrp-18.0.1.0.0.2.dist-info/WHEEL
odoo_addon_sale_line_returned_qty_mrp-18.0.1.0.0.2.dist-info/top_level.txt
odoo_addon_sale_line_returned_qty_mrp-18.0.1.0.0.2.dist-info/RECORD
