Metadata-Version: 2.1
Name: odoo-addon-sale_line_returned_qty_mrp
Version: 18.0.1.0.0.2
Requires-Python: >=3.10
Requires-Dist: odoo-addon-sale_line_returned_qty==18.0.*
Requires-Dist: odoo==18.0.*
Summary: Track returned quantity of sale order lines for BoM products.
Home-page: https://github.com/OCA/stock-logistics-workflow
License: LGPL-3
Author: ForgeFlow, Odoo Community Association (OCA)
Author-email: support@odoo-community.org
Classifier: Programming Language :: Python
Classifier: Framework :: Odoo
Classifier: Framework :: Odoo :: 18.0
Classifier: License :: OSI Approved :: GNU Lesser General Public License v3 (LGPLv3)
